[
    {
        "nid": "Gandolf",
        "name": "Gandolf",
        "desc": "Elder son of King Batur of Verdane, and Kinbois and Jamke's brother.",
        "variant": "",
        "level": 20,
        "klass": "Warrior",
        "tags": [],
        "bases": {
            "HP": 60,
            "STR": 17,
            "MAG": 0,
            "SKL": 11,
            "SPD": 13,
            "LCK": 0,
            "DEF": 13,
            "RES": 5,
            "CON": 13,
            "MOV": 70
        },
        "growths": {
            "HP": 110,
            "STR": 50,
            "MAG": 5,
            "SKL": 50,
            "SPD": 30,
            "LCK": 40,
            "DEF": 40,
            "RES": 5,
            "CON": 0,
            "MOV": 0
        },
        "starting_items": [
            [
                "Hand Axe",
                false
            ],
            [
                "Skill Ring",
                true
            ]
        ],
        "learned_skills": [],
        "unit_notes": [],
        "wexp_gain": {
            "Sword": [
                false,
                0
            ],
            "Lance": [
                false,
                0
            ],
            "Axe": [
                true,
                226
            ],
            "Bow": [
                true,
                126
            ],
            "Staff": [
                false,
                0
            ],
            "Light": [
                false,
                0
            ],
            "Anima": [
                false,
                0
            ],
            "Dark": [
                false,
                0
            ],
            "Default": [
                false,
                0
            ]
        },
        "alternate_classes": [],
        "portrait_nid": "GandolfPortrait",
        "affinity": "Fire",
        "fields": []
    }
]